{"link": "https://codeforces.com//contest/1671/problem/C", "problemId": "1376217", "problem_idx": "C", "shortId": "1671C", "contest_number": "1671", "problem_submissions": {"F": [154542143, 154558308, 154555068, 154557074, 154562560, 154560412, 154560334, 154580455, 154580066, 154579893, 154579534, 154559391, 154560455, 154556037, 154570936, 154568652, 154567294, 154570123, 154570095, 154571694, 154567547, 154573773, 154574629], "E": [154528618, 154523246, 154538308, 154531841, 154536634, 154537536, 154534868, 154536863, 154540214, 154537733, 154537068, 154539560, 154544853, 154541083, 154543961, 154546659, 154540036, 154543052], "D": [154515283, 154518590, 154521489, 154520458, 154521403, 154524920, 154528513, 154532728, 154525208, 154525643, 154525793, 154526566, 154525948, 154532548, 154534260, 154534156, 154549567, 154532508], "C": [154510946, 154513613, 154516509, 154516298, 154514632, 154518397, 154518432, 154511688, 154514098, 154517459, 154516109, 154520271, 154520298, 154520714, 154518755, 154518674, 154516230, 154526116], "B": [154508972, 154509429, 154511794, 154511150, 154510866, 154511702, 154510603, 154509631, 154511147, 154510842, 154511266, 154514390, 154513321, 154513559, 154512703, 154511916, 154511617, 154520025], "A": [154508532, 154508535, 154508654, 154509163, 154508619, 154508583, 154508765, 154508590, 154508804, 154509162, 154508941, 154509310, 154508759, 154508605, 154508711, 154508600, 154508845, 154516250]}, "name": "C. Dolce Vita", "statement": "Turbulent times are coming, so you decided to buy sugar in advance.\r\nThere are n shops around that sell sugar: the i-th shop sells one pack\r\nof sugar for a_i coins, but only each day. So in order to buy several\r\npacks, you need to visit several shops.Another problem is that prices\r\nare increasing each day: during the first day the cost is a_i, during\r\nthe second day cost is a_i + 1, during the third day a_i + 2 and so on\r\nfor each shop i.On the contrary, your everyday budget is only x coins.\r\nIn other words, each day you go and buy as many packs as possible with\r\ntotal cost not exceeding x. Note that if you don\u2019t spend some amount of\r\ncoins during a day, you can\u2019t use these coins during the next\r\ndays.Eventually, the cost for each pack will exceed x, and you won\u2019t be\r\nable to buy even a single pack. So, how many packs will you be able to\r\nbuy till that moment in total?\r\n", "solutions": ["/**\n *    author:  tourist\n *    created: 22.04.2022 18:37:41       \n**/\n#include <bits/stdc++.h>\n\nusing namespace std;\n\n#ifdef LOCAL\n#include \"algo/debug.h\"\n#else\n#define debug(...) 42\n#endif\n\nint main() {\n  ios::sync_with_stdio(false);\n  cin.tie(0);\n  int tt;\n  cin >> tt;\n  while (tt--) {\n    int n, x;\n    cin >> n >> x;\n    vector<int> a(n);\n    for (int i = 0; i < n; i++) {\n      cin >> a[i];\n    }\n    sort(a.begin(), a.end());\n    long long s = 0;\n    long long ans = 0;\n    for (int i = 0; i < n; i++) {\n      s += a[i];\n      if (s <= x) {\n        ans += (x - s) / (i + 1) + 1;\n      }\n    }\n    cout << ans << '\\n';\n  }\n  return 0;\n}\n"], "input": "", "output": "", "tags": ["binary search", "brute force", "greedy", "math"], "dificulty": "1200", "interactive": false}