{
    "link": "https://codeforces.com//contest/1833/problem/A",
    "problemId": "1929814",
    "problem_idx": "A",
    "shortId": "1833A",
    "contest_number": "1833",
    "problem_submissions": {
        "F": [
            206599548,
            206499044,
            206510645,
            206497958,
            206917535,
            206498356,
            206512969,
            206501833,
            206507754,
            206504303,
            206775083,
            206513772,
            206514120,
            206515332,
            206518320,
            206514205,
            206521502,
            206515630,
            206524274,
            206520741,
            206520948,
            206526178,
            206521131
        ],
        "G": [
            206512331,
            206521465,
            206506545,
            206477170,
            206519573,
            206523410,
            206530322,
            206518526,
            206777759,
            206531078,
            206532207,
            206527389,
            206532553,
            206535240,
            206530738,
            206539901,
            206510414,
            206533541,
            209018213,
            206536054,
            206538842,
            206866462,
            206539276
        ],
        "E": [
            206494444,
            206500619,
            206508800,
            206912480,
            206752261,
            206508820,
            206500946,
            206513913,
            206499318,
            206515052,
            206776677,
            206501077,
            206501029,
            206508081,
            206504803,
            206505276,
            206514758,
            206507981,
            206532142,
            206514436,
            206505945,
            206510447,
            206508190
        ],
        "D": [
            206478490,
            206489393,
            206482509,
            206516497,
            206493139,
            206494430,
            206493405,
            206772261,
            206483249,
            206490999,
            206496792,
            206494490,
            206495499,
            206492096,
            206495671,
            206562276,
            206493504,
            206494409,
            206497119,
            206489160,
            206496422
        ],
        "C": [
            206468900,
            206472444,
            206487689,
            206481281,
            206470369,
            206469924,
            206472556,
            206474926,
            206470601,
            206467341,
            206478011,
            206475881,
            206470693,
            206472518,
            206472870,
            206562261,
            206473668,
            206473209,
            206471774,
            206472820,
            206477277
        ],
        "B": [
            206461337,
            206465386,
            206481088,
            206469699,
            206465480,
            206464242,
            206462159,
            206470246,
            206468314,
            206462993,
            206468820,
            206467031,
            206466013,
            206465802,
            206464804,
            206466201,
            206465451,
            206463520,
            206466366,
            206465332
        ],
        "A": [
            206458073,
            206459090,
            206464738,
            206461735,
            206459482,
            206458188,
            206458127,
            206458669,
            206459064,
            206459476,
            206460428,
            206459198,
            206458554,
            206458909,
            206458986,
            206459453,
            206458429,
            206458492,
            206458602
        ]
    },
    "name": "A. Musical Puzzle",
    "statement": "Vlad decided to compose a melody on his guitar. Let’s represent the\r\nmelody as a sequence of notes corresponding to the characters ’a’, ’b’,\r\n’c’, ’d’, ’e’, ’f’, and ’g’.However, Vlad is not very experienced in\r\nplaying the guitar and can only record notes at a time. Vlad wants to\r\nobtain the melody s, and to do this, he can merge the recorded melodies\r\ntogether. In this case, the last sound of the first melody must match\r\nthe first sound of the second melody.For example, if Vlad recorded the\r\nmelodies and , he can merge them together and obtain the melody , and\r\nthen merge the result with to get .Help Vlad determine the number of\r\nmelodies consisting of two notes that he needs to record in order to\r\nobtain the melody s.\r\n",
    "solutions": [
        "#include <bits/stdc++.h>\n\nusing i64 = long long;\n\nvoid solve() {\n    int n;\n    std::cin >> n;\n    std::string s;\n    std::cin >> s;\n    std::map<std::string, int> cnt;\n    for (int i = 1; i < n; i++) {\n        std::string t;\n        t += s[i - 1];\n        t += s[i];\n        ++cnt[t];\n    }\n    std::cout << (int) cnt.size() << \"\\n\";\n}\n\nsigned main() {\n    std::ios::sync_with_stdio(false);\n    std::cin.tie(nullptr);\n \n    int t = 1;\n    std::cin >> t;\n \n    while (t--) {\n        solve();\n    }\n}"
    ],
    "input": "",
    "output": "",
    "tags": [
        "implementation",
        "strings"
    ],
    "dificulty": "800",
    "interactive": false,
    "file_name": "D:\\scoala\\RESEARCH\\MLCP\\01_CODEFORCES_DATASET\\DIV3\\A. Musical Puzzle.json",
    "editorial_link": "https://codeforces.com//blog/entry/116636",
    "editorial": "Letâs construct the melody sequentially. In the first step, we can\r\nrecord the notes and . In the next step, we need to record and , because\r\nthere must be a common symbol when gluing and so on. That is, we need to\r\nhave recorded melodies + for all . We only need to count how many\r\ndifferent ones among them, because we donât need to record one melody\r\ntwice.\r\n",
    "hint": []
}