{"link": "https://codeforces.com//contest/129/problem/A", "problemId": "677", "problem_idx": "A", "shortId": "129A", "contest_number": "129", "problem_submissions": {"D": [870060, 869793, 868329, 868490, 871604, 869018, 869569], "E": [867711, 868998, 867271, 866024, 867668, 866384, 868771, 868972, 869787, 869113, 869182, 869294, 869358], "C": [866691, 866148, 865711, 868095, 866773, 867004, 867491, 867351, 866936, 866349, 867158, 866312, 867092, 867601, 867201, 867450, 867706, 867793], "B": [865720, 865280, 865180, 865582, 865310, 866211, 868127, 865744, 865731, 866928, 865788, 865528, 865521, 866153, 866294, 865110, 865388, 865554], "A": [864668, 864600, 864704, 864708, 864607, 864653, 868290, 864785, 864784, 867045, 864843, 864624, 864640, 865218, 864855, 865276, 864658, 864664]}, "name": "A. Cookies", "statement": "Olga came to visit the twins Anna and Maria and saw that they have many\r\ncookies. The cookies are distributed into bags. As there are many\r\ncookies, Olga decided that it\u2019s no big deal if she steals a bag.\r\nHowever, she doesn\u2019t want the sisters to quarrel because of nothing when\r\nthey divide the cookies. That\u2019s why Olga wants to steal a bag with\r\ncookies so that the number of cookies in the remaining bags was even,\r\nthat is, so that Anna and Maria could evenly divide it into two (even 0\r\nremaining cookies will do, just as any other even number). How many ways\r\nthere are to steal exactly one cookie bag so that the total number of\r\ncookies in the remaining bags was even?\r\n", "solutions": ["#include <cstdio>\n#include <cmath>\n#include <cstring>\n#include <iostream>\n#include <string>\n#include <vector>\n#include <utility>\n#include <sstream>\n#include <algorithm>\n#include <map>\n#include <queue>\n#include <ctime>\n#include <set>\n#include <iterator>\n\nusing namespace std;\ntypedef long long LL;\ntypedef pair< int, int > PRII;\ntypedef pair< double, double > PRDD;\ntypedef vector< string > VS;\ntypedef vector< int > VI;\n\n#define x first\n#define y second\n#define p_b push_back\n#define m_p make_pair\n#define oo 1000000000\n\n#define sqr(x) ((x)*(x))\n#define Size(a) ((int)a.size())\n#define forn(i,n) for( i = 0 ; i < n ; ++i )\n\nconst double pi = acos(-1);\n#define maxn 100 + 10\n\nint n,a[maxn],sum = 0,ans = 0;\n\nint main()\n{\n    int i;\n    \n    scanf(\"%d\",&n);\n    for( i = 1 ; i <= n ; ++i )\n        {\n            scanf(\"%d\",&a[i]);\n            sum += a[i];\n        }\n    for( i = 1 ; i <= n ; ++i )\n        if( (sum-a[i]) % 2 == 0 )\n            ++ans;\n    printf(\"%d\\n\",ans);\n    \n    return 0;\n}\n"], "input": "", "output": "", "tags": ["implementation"], "dificulty": "900", "interactive": false}