{"link": "https://codeforces.com//contest/1330/problem/A", "problemId": "582578", "problem_idx": "A", "shortId": "1330A", "contest_number": "1330", "problem_submissions": {"E": [75407483, 75403686, 75406825, 75412857, 75411514, 75411404, 75407783, 75407274, 75400418, 75447922, 75412935, 75466280], "D": [75391296, 75385541, 80644507, 75388709, 75387337, 75393475, 75395701, 75385540, 75376125, 75379564, 75382546, 75380901, 75384917, 75382324, 75380657, 75388115, 75386567, 75461008, 75388223, 75387064], "C": [75379279, 75374912, 75381565, 75376079, 75376451, 75390556, 75381440, 75360964, 75379654, 75372629, 75367460, 75443397, 75374056, 75373762, 75374173, 220742361, 75370741, 75373514, 75361682, 75373297], "B": [75362106, 75368513, 75363431, 75362706, 75364291, 75378289, 75379661, 75360912, 75356953, 75360775, 75363811, 75360857, 75361079, 75359545, 195278107, 75360634, 75361090, 75371429, 75361221], "A": [75355521, 75354244, 75354217, 75356116, 75354591, 75364896, 75353923, 75353902, 75354562, 75354818, 75353692, 75353618, 75362319, 179068881, 75354934, 75353839, 75364875, 75354143]}, "name": "A. Dreamoon and Ranking Collection", "statement": "Dreamoon is a big fan of the Codeforces contests.One day, he claimed\r\nthat he will collect all the places from 1 to 54 after two more rated\r\ncontests. It\u2019s amazing!Based on this, you come up with the following\r\nproblem:There is a person who participated in n Codeforces rounds. His\r\nplace in the first round is a_1, his place in the second round is a_2,\r\n..., his place in the n-th round is a_n.You are given a positive\r\nnon-zero integer x.Please, find the largest v such that this person can\r\ncollect all the places from 1 to v after x more rated contests.In other\r\nwords, you need to find the largest v, such that it is possible, that\r\nafter x more rated contests, for each 1\r\nleq i\r\nleq v, there will exist a contest where this person took the i-th\r\nplace.For example, if n=6, x=2 and a=[3,1,1,5,7,10] then answer is v=5,\r\nbecause if on the next two contest he will take places 2 and 4, then he\r\nwill collect all places from 1 to 5, so it is possible to get v=5.\r\n", "solutions": ["#include<cstdio>\nusing namespace std;\nint T,n,x,k,ans;\nbool a[310];\nint main(){\n\tscanf(\"%d\",&T);\n\twhile (T--){\n\t\tfor (int i=1;i<=300;i++) a[i]=false;\n\t\tscanf(\"%d%d\",&n,&x);\n\t\tfor (int i=1;i<=n;i++){\n\t\t\tscanf(\"%d\",&k);\n\t\t\ta[k]=true;\n\t\t}\n\t\tans=0;\n\t\tfor (int i=1;i<=300&&x>=0;i++){\n\t\t\tif (!a[i]) x--;\n\t\t\tans=i;\n\t\t}\n\t\tprintf(\"%d\\n\",ans-1);\n\t}\n\treturn 0;\n}\n"], "input": "", "output": "", "tags": ["implementation"], "dificulty": "900", "interactive": false}