{"link": "https://codeforces.com//contest/344/problem/A", "problemId": "3462", "problem_idx": "A", "shortId": "344A", "contest_number": "344", "problem_submissions": {"E": [4466832, 4466881, 4466839, 4467938, 4467852, 4467906, 4467882, 4468520, 4468666, 4468956, 4470309, 4470343, 4470890, 4470646, 4467178], "D": [4462598, 4463520, 4463970, 4465391, 4463898, 4463951, 4464720, 4464711, 4464808, 4465291, 4466089, 4465147, 4464978, 4462443, 4462461, 4461439, 4462978, 4463724], "C": [4462080, 4460954, 4462735, 4464740, 4461891, 4463048, 4463380, 4462836, 4462940, 4463239, 4462139, 4463864, 4466720, 4465356, 4460855, 4461389, 4462577, 4462304], "B": [4460105, 4460097, 4460219, 4462525, 4460360, 4459970, 4461098, 4461404, 4460184, 4461242, 4460727, 4461556, 4462077, 4459824, 4459969, 4460167, 4460213, 4459935], "A": [4458731, 4458719, 4458834, 4459218, 4458679, 4458789, 4458804, 4460231, 4458819, 4459697, 4459355, 4459770, 4458622, 4459629, 4458794, 4458666, 4458710, 4458866, 4458867]}, "name": "A. Magnets", "statement": "Mad scientist Mike entertains himself by arranging rows of dominoes. He\r\ndoesn\u2019t need dominoes, though: he uses rectangular magnets instead. Each\r\nmagnet has two poles, positive (a \"plus\") and negative (a \"minus\"). If\r\ntwo magnets are put together at a close distance, then the like poles\r\nwill repel each other and the opposite poles will attract each\r\nother.Mike starts by laying one magnet horizontally on the table. During\r\neach following step Mike adds one more magnet horizontally to the right\r\nend of the row. Depending on how Mike puts the magnet on the table, it\r\nis either attracted to the previous one (forming a group of multiple\r\nmagnets linked together) or repelled by it (then Mike lays this magnet\r\nat some distance to the right from the previous one). We assume that a\r\nsole magnet not linked to others forms a group of its own. Mike arranged\r\nmultiple magnets in a row. Determine the number of groups that the\r\nmagnets formed.\r\n", "solutions": ["#define _CRT_SECURE_NO_WARNINGS\n#include <cstdio>\n#include <cmath>\n#include <vector>\n#include <queue>\n#include <set>\n#include <map>\n#include <algorithm>\n#include <string>\n#include <cstring>\n#include <iostream>\nusing namespace std;\n#pragma comment(linker, \"/STACK:167772160\")\n\ntypedef long long ll;\ntypedef pair<int, int> pii;\n\nconst int INF = 1e9;\nconst double EPS = 1e-9;\nconst double PI = acos(-1.);\n\nint main()\n{\n#ifndef ONLINE_JUDGE\n\tfreopen(\"testA.txt\", \"r\", stdin);\n#endif\n    int N;\n    scanf(\"%d\", &N);\n    int ans = 0;\n    int prv = -1;\n    char buff[10];\n    for (int i = 0; i < N; ++i)\n    {\n        scanf(\"%s\", buff);\n        int type;\n        if (buff[0] == '0')\n            type = 0;\n        else\n            type = 1;\n        if (prv != type)\n            ++ans;\n        prv = type;\n    }\n    printf(\"%d\\n\", ans);\n\treturn 0;\n}\n"], "input": "", "output": "", "tags": ["implementation"], "dificulty": "800", "interactive": false}