{"link": "https://codeforces.com//contest/363/problem/A", "problemId": "3952", "problem_idx": "A", "shortId": "363A", "contest_number": "363", "problem_submissions": {"A": [5091717, 5059128, 5058405, 5060702, 5058501, 5058437, 5058523, 5058870, 5058824, 5058569, 5058849, 5058835, 5058475, 5058869, 5058397, 5059373, 5059116, 5059730, 5058538], "D": [5062003, 5062111, 5062048, 5062488, 5062551, 5062600, 5061744, 5062900, 5063480, 5063361, 5063540, 5061475, 5063510, 5063001, 5063238, 5064967, 5063752, 5063544], "C": [5060575, 5060628, 5059863, 5060397, 5060617, 5061312, 5059999, 5062594, 5061103, 5061402, 5061178, 5064048, 5061146, 5061399, 5061242, 5061422, 5061398, 5061876], "B": [5059750, 5059183, 5058598, 5059033, 5058933, 5059248, 5059323, 5059565, 5059297, 5059605, 5059146, 5058928, 5059719, 5058972, 5059858, 5058459, 5059102, 5059528], "E": [5072598]}, "name": "A. Soroban", "statement": "You know that Japan is the country with almost the largest \u2019electronic\r\ndevices per person\u2019 ratio. So you might be quite surprised to find out\r\nthat the primary school in Japan teaches to count using a an abacus\r\ndeveloped in Japan. This phenomenon has its reasons, of course, but we\r\nare not going to speak about them. Let\u2019s have a look at the Soroban\u2019s\r\nconstruction. Soroban consists of some number of rods, each rod contains\r\nfive beads. We will assume that the rods are horizontal lines. One bead\r\non each rod (the leftmost one) is divided from the others by a bar (the\r\nreckoning bar). This single bead is called and four others are . Each\r\nrod is responsible for representing a single digit from 0 to 9. We can\r\nobtain the value of a digit by following simple algorithm: Set the value\r\nof a digit equal to 0. If the go-dama is shifted to the right, add 5.\r\nAdd the number of ichi-damas shifted to the left. Thus, the upper rod on\r\nthe picture shows digit 0, the middle one shows digit 2 and the lower\r\none shows 7. We will consider the top rod to represent the last decimal\r\ndigit of a number, so the picture shows number 720.Write the program\r\nthat prints the way Soroban shows the given number .\r\n", "solutions": ["#include <iostream>\n#include <string>\nusing namespace std;\nstring a[10]={\n\"O-|-OOOO\",\n\"O-|O-OOO\",\n\"O-|OO-OO\",\n\"O-|OOO-O\",\n\"O-|OOOO-\",\n\"-O|-OOOO\",\n\"-O|O-OOO\",\n\"-O|OO-OO\",\n\"-O|OOO-O\",\n\"-O|OOOO-\"};\nint main(){\n    int n;\n    cin>>n;\n    if (n==0){\n        cout<<a[0]; return 0;\n    }\n    while (n>0){\n        cout<< a[n%10];\n        n=n/10;\n        if (n>0) cout<<\"\\n\";\n    }\n    return 0;\n}\n"], "input": "", "output": "", "tags": ["implementation"], "dificulty": "800", "interactive": false}