{
    "link": "https://codeforces.com//contest/41/problem/A",
    "problemId": "213",
    "problem_idx": "A",
    "shortId": "41A",
    "contest_number": "41",
    "problem_submissions": {
        "E": [
            187709,
            187786,
            188013,
            188055,
            187720,
            188400,
            187514,
            188819,
            188191,
            188320,
            187947,
            187986,
            188068,
            187475,
            188102,
            188249,
            188098
        ],
        "D": [
            187451,
            188035,
            187556,
            187294,
            187606,
            188558,
            188821,
            187849,
            187246,
            187712
        ],
        "C": [
            186912,
            186684,
            186917,
            187641,
            186883,
            186553,
            188818,
            186598,
            186899,
            188654,
            186712,
            186971,
            187041,
            187211,
            187296,
            187151,
            187405
        ],
        "B": [
            186796,
            186260,
            186544,
            186516,
            188464,
            186708,
            186215,
            188816,
            186320,
            188632,
            186180,
            186422,
            186551,
            186670,
            188213,
            186455,
            186499
        ],
        "A": [
            185992,
            186549,
            186066,
            186169,
            186054,
            186446,
            186002,
            188814,
            186063,
            186094,
            185993,
            186104,
            186145,
            185988,
            186586,
            185990,
            186130
        ]
    },
    "name": "A. Translation",
    "statement": "The translation from the Berland language into the Birland language is\r\nnot an easy task. Those languages are very similar: a berlandish word\r\ndiffers from a birlandish word with the same meaning a little: it is\r\nspelled (and pronounced) reversely. For example, a Berlandish word\r\ncorresponds to a Birlandish word . However, it’s easy to make a mistake\r\nduring the translation . Vasya translated word from Berlandish into\r\nBirlandish as . Help him: find out if he translated the word correctly.\r\n",
    "solutions": [
        "#include<iostream>\n#include<cstdio>\n#include<cmath>\n#include<cstdlib>\n#include<algorithm>\n#include<vector>\n#include<string>\n#include<list>\n#include<map>\n#include<set>\n#include<queue>\n#include<stack>\n#include<utility>\n#include<sstream>\nusing namespace std;\n#define FOR(I,A,B) for(int I=(A);I<=(B);I++)\n#define REP(I,N) for(int I=0;I<(N);I++)\n#define ALL(X) (X).begin(),(X).end()\n#define VAR(A,B) __typeof(B) A=B\n#define FORE(I,X) for(VAR(I,(X).begin());I!=(X).end();I++)\n#define F first\n#define S second\n#define INF 1000000007\n#define PB push_back\n#define MP make_pair\ntypedef pair<int,int> PII;\ntypedef long long LL;\nstring a,b;\nchar tab[1007];\n\nint main(){\n\tscanf(\"%s\",tab); a=tab;\n\tscanf(\"%s\",tab); b=tab;\n\treverse(ALL(a));\n\tif (a==b) printf(\"YES\\n\");\n\telse printf(\"NO\\n\");\n}\n"
    ],
    "input": "",
    "output": "",
    "tags": [
        "implementation",
        "strings"
    ],
    "dificulty": "800",
    "interactive": false,
    "file_name": "D:\\scoala\\RESEARCH\\MLCP\\01_CODEFORCES_DATASET\\DIV2\\A. Translation.json",
    "editorial_link": "https://codeforces.com//blog/entry/1620",
    "editorial": "Many languages have built-in reverse() function for strings. we can reverse one of the strings and check if it's equal to the other one , or we can check it manually. I prefer the second.",
    "hint": []
}