{
    "link": "https://codeforces.com//contest/404/problem/A",
    "problemId": "7288",
    "problem_idx": "A",
    "shortId": "404A",
    "contest_number": "404",
    "problem_submissions": {
        "B": [
            6081380,
            6071583,
            6070927,
            6071339,
            6070454,
            6070614,
            6072572,
            6071620,
            6071224,
            6072980,
            6072201,
            6072080,
            6071625,
            6070557,
            6072898,
            6071106,
            6072617,
            6072939
        ],
        "A": [
            6081009,
            6068298,
            6068430,
            6069127,
            6068593,
            6068443,
            6069041,
            6068506,
            6069739,
            6068994,
            6068641,
            6068845,
            6068699,
            6071140,
            6069542,
            6069802,
            6068288
        ],
        "E": [
            6077708,
            6078243,
            6080273,
            6089004,
            6098326,
            6095224,
            6104347
        ],
        "D": [
            6074157,
            6076415,
            6075648,
            6078211,
            6077330,
            6077784,
            6078940,
            6079076,
            6079336,
            6078890,
            6080135,
            6077817,
            6078043,
            6080355,
            6079190,
            6077371
        ],
        "C": [
            6072624,
            6074366,
            6073677,
            6073792,
            6072756,
            6073958,
            6074499,
            6073931,
            6073038,
            6075180,
            6075460,
            6076470,
            6074776,
            6073618,
            6075857,
            6074780,
            6076291,
            6078785
        ]
    },
    "name": "A. Valera and X",
    "statement": "Valera is a little boy. Yesterday he got a huge Math hometask at school,\r\nso Valera didn’t have enough time to properly learn the English alphabet\r\nfor his English lesson. Unfortunately, the English teacher decided to\r\nhave a test on alphabet today. At the test Valera got a square piece of\r\nsquared paper. The length of the side equals squares ( is an odd number)\r\nand each unit square contains some small letter of the English\r\nalphabet.Valera needs to know if the letters written on the square piece\r\nof paper form letter \"\". Valera’s teacher thinks that the letters on the\r\npiece of paper form an \"\", if: on both diagonals of the square paper all\r\nletters are the same; all other squares of the paper (they are not on\r\nthe diagonals) contain the same letter that is different from the\r\nletters on the diagonals. Help Valera, write the program that completes\r\nthe described task for him.\r\n",
    "solutions": [
        "#include <map>\n#include <set>\n#include <cmath>\n#include <ctime>\n#include <queue>\n#include <stack>\n#include <cstdio>\n#include <string>\n#include <vector>\n#include <cstring>\n#include <sstream>\n#include <iostream>\n#include <algorithm>\n#include <bitset>\nusing namespace std;\n\n#define PB(x) push_back(x)\n#define MP(x, y) make_pair(x, y)\n#define lx x + x\n#define rx lx + 1\n#define ly y + y\n#define ry ly + 1\ntypedef long long LL;\n\nconst int N = 805;\nconst int M = 1005;\nconst int INF = 1e9 + 7;\nconst int MOD = 1e9 + 7;\nconst double eps = 1e-6;\n\nchar s[555][555]; int n;\nint cnt[26];\nint main(){\n    scanf(\"%d\", &n);\n    for (int i = 0; i < n; i++){\n        scanf(\"%s\", s[i]);\n        for (int j = 0; j < n; j++)\n            cnt[s[i][j] - 'a']++;\n    }\n    int t = 0;\n    for (int i = 0; i < 26; i++) if (cnt[i]) t++;\n    if (t != 2){\n        puts(\"NO\");\n        return 0;\n    }\n    for (int i = 0; i < n; i++) if (s[i][n - i - 1] != s[0][0]){\n        puts(\"NO\");\n        return 0;\n    }\n    for (int i = 0; i < n; i++) if (s[i][i] != s[0][0]){\n        puts(\"NO\");\n        return 0;\n    }\n    for (int i = 0; i < n; i++)\n    for (int j = 0; j < n; j++)\n    if (i != j && j != (n - i - 1) && s[i][j] == s[0][0]){\n        puts(\"NO\");\n        return 0;\n    }\n    puts(\"YES\");\n}\n"
    ],
    "input": "",
    "output": "",
    "tags": [
        "implementation"
    ],
    "dificulty": "1000",
    "interactive": false,
    "file_name": "D:\\scoala\\RESEARCH\\MLCP\\01_CODEFORCES_DATASET\\DIV2\\A. Valera and X.json",
    "editorial_link": "https://codeforces.com/blog/entry/11095",
    "editorial": "In this problem it was needed to check the constraints described in\r\nstatement. You can use two sets here. You should insert diagonal\r\nelements of matrix into the first set, and the other elements into the\r\nsecond. Element belongs to the main diagonal if and belongs to the\r\nsecondary diagonal if . After you split all elements into sets you\r\nshould check if the sets sizes are equal to one and the elements from\r\nthis sets differ from each other.\r\n",
    "hint": []
}