{
    "link": "https://codeforces.com//contest/342/problem/A",
    "problemId": "3438",
    "problem_idx": "A",
    "shortId": "342A",
    "contest_number": "342",
    "problem_submissions": {
        "E": [
            4424475,
            4422829,
            4430368,
            4421720,
            4425588,
            4424864,
            7980137,
            4422643,
            4422969,
            33894142,
            33894120,
            12335279
        ],
        "D": [
            4422563,
            4424584,
            4422881,
            4425178,
            4424327
        ],
        "B": [
            4417892,
            4425509,
            4417934,
            4418698,
            4420332,
            4419060,
            4418029,
            4418641,
            4419108,
            4418926,
            4419003,
            4423078,
            4421488,
            4420712,
            4420147,
            4428238,
            4428202,
            4420216,
            4418853,
            4419150,
            4419856
        ],
        "A": [
            4417092,
            4417221,
            4417057,
            4417245,
            4417383,
            4417575,
            4417020,
            4417100,
            4417102,
            4419265,
            4417254,
            4417136,
            4419082,
            4418070,
            4418662,
            4418542,
            4417680,
            4417389,
            4417298
        ],
        "C": [
            4419537,
            4420363,
            4425253,
            4423789,
            4425489,
            4420140,
            4422038,
            4419838,
            4423331,
            4424488,
            4420343,
            4420820,
            4423363
        ]
    },
    "name": "A. Xenia and Divisors",
    "statement": "Xenia the mathematician has a sequence consisting of ( is divisible by\r\n3) positive integers, each of them is at most 7. She wants to split the\r\nsequence into groups of three so that for each group of three the\r\nfollowing conditions held: ; divides , divides . Naturally, Xenia wants\r\neach element of the sequence to belong to exactly one group of three.\r\nThus, if the required partition exists, then it has groups of three.Help\r\nXenia, find the required partition or else say that it doesn\u2019t exist.\r\n",
    "solutions": [
        "#include <iostream>\n#include <cstdio>\n#include <cstring>\n#include <cmath>\n#include <algorithm>\n#include <set>\n#include <map>\n#include <queue>\n#define lson step << 1\n#define rson step << 1 | 1\n#define lowbit(x) (x & (-x))\n#define Key_value ch[ch[root][1]][0] \nusing namespace std;\ntypedef long long LL;\nconst int N = 500005;\nconst int inf = 1000000009;\nint n , a[N] , c[10];\nvector<pair<pair<int , int> , int> > v;\nint main () {\n    #ifndef ONLINE_JUDGE\n        freopen (\"input.txt\" , \"r\" , stdin);\n        // freopen (\"output.txt\" , \"w\" , stdout);\n    #endif\n    cin >> n;\n    for (int i = 0 ; i < n ; i ++) {\n        cin >> a[i];\n        c[a[i]] ++;\n    }\n    if (c[5] || c[7]) {\n        puts (\"-1\");\n        return 0;\n    }\n    for (int i = 0 ; i < c[4] ; i ++)\n        v.push_back (make_pair(make_pair(1 , 2) , 4));\n    c[2] -= c[4];c[1] -= c[4];\n    for (int i = 0 ; i < c[3] ; i ++)\n        v.push_back (make_pair(make_pair(1 , 3) , 6));\n    c[6] -= c[3];c[1] -= c[3];\n    if (c[1] < 0 || c[2] < 0 || c[6] < 0) {\n        puts (\"-1\");\n        return 0;\n    }\n    if (c[1] != c[2] || c[2] != c[6] || c[1] != c[6]) {\n        puts (\"-1\");\n        return 0;\n    }\n    for (int i = 0 ; i < v.size() ; i ++)\n        cout << v[i].first.first << \" \" << v[i].first.second << \" \" << v[i].second << endl;\n    for (int i = 0 ; i < c[1] ; i ++)\n        cout << \"1 2 6\" << endl;\n    return 0;\n}       \n\n"
    ],
    "input": "",
    "output": "",
    "tags": [
        "greedy",
        "implementation"
    ],
    "dificulty": "1200",
    "interactive": false,
    "file_name": "D:\\scoala\\RESEARCH\\MLCP\\01_CODEFORCES_DATASET\\DIV2\\A. Xenia and Divisors.json",
    "editorial_link": "https://codeforces.com/blog/entry/8800",
    "editorial": "In this problem you should guess that exists only three valid groups of\r\nthree 1) 1, 2, 4 2) 1, 2, 6 3) 1, 3, 6 (You can see that integers 5 and\r\n7 are bad). So, we will greedy take these groups of three. If some\r\nintegers will be not used, the answer is -1. In other case, print found\r\nanswer.\r\n"
}