{"link": "https://codeforces.com//contest/221/problem/B", "problemId": "1623", "problem_idx": "B", "shortId": "221B", "contest_number": "221", "problem_submissions": {"E": [3205051, 2092800, 2086150, 2086057, 2087298, 2087155, 2087149, 2087018, 2086854, 2086766, 2084177, 85197769], "D": [2077623, 2076297, 2081220, 2080200, 2077733, 2077945, 2078661, 2078764, 2079390, 2078475, 2078957, 2078857, 2079767, 2079126, 2080238, 2080763, 2080984], "C": [2075002, 2086554, 2073629, 2075934, 2074814, 2076079, 2073608, 2075600, 2075194, 2075398, 2074548, 2075699, 2076113, 2076291, 2077149, 2075454, 2074363, 2076715], "B": [2074170, 2074163, 2072750, 2073391, 2074703, 2076060, 2073836, 2074637, 2073703, 2073926, 2074911, 2074503, 2075040, 2074940, 2073942, 2073661, 2075809], "A": [2072835, 2074357, 2073486, 2074025, 2073249, 2073912, 2072457, 2073442, 2072552, 2072801, 2072681, 2073490, 2073385, 2074053, 2072948, 2072853, 2073301]}, "name": "B. Little Elephant and Numbers", "statement": "The Little Elephant loves numbers. He has a positive integer . The\r\nLittle Elephant wants to find the number of positive integers , such\r\nthat is the divisor of , and and have at least one common (the same)\r\ndigit in their decimal representations. Help the Little Elephant to find\r\nthe described number.\r\n", "solutions": ["#include <vector>\n#include <queue>\n#include <list>\n#include <map>\n#include <set>\n#include <deque>\n#include <stack>\n#include <bitset>\n#include <algorithm>\n#include <functional>\n#include <numeric>\n#include <utility>\n#include <sstream>\n#include <iostream>\n#include <iomanip>\n#include <cstring>\n#include <cstdio>\n#include <cmath>\n#include <cstdlib>\n#include <ctime>\n\nusing namespace std;\n\n#define fi first\n#define se second\n#define mp make_pair\n#define sz size\n#define re return\n#define pb(x) push_back(x)\n#define pf(x) push_front(x)\n#define abs(x) ((x) < 0 ? -(x) : (x))\n#define INF 2000000000\n#define sqr(x) ((x) * (x))\n#define all(x) x.begin(), x.end()\n\nlong long int x, d, res;\nint a[1000], l;\n\nint main() {\n\n#ifndef ONLINE_JUDGE\t          \n\tfreopen(\"a.in\", \"r\", stdin);\n\tfreopen(\"a.out\", \"w\", stdout);\n#endif\n\tcin >> x;\n\td = x;\n\twhile(d) {\n\t\ta[++l] = d % 10;\n\t\td /= 10;\n\t}\n\n\tfor(int i = 1; i * i <= x; i++) {\n\t\tif(x % i == 0) {\n\t\t\t    d = i;\n\t\t\t    bool ok = 1;\n\t\t\t\twhile(d) {\n\t\t\t\t\tfor(int i = 1; i <= l; i++)\n\t\t\t\t\t\tif(a[i] == d % 10) {\n\t\t\t\t\t\t\tok = 0;\n\t\t\t\t\t\t\tbreak;\n\t\t\t\t\t\t}\n\t\t\t\t\tif(!ok) {\n\t\t\t\t\t\tres++;\n\t\t\t\t\t\tbreak;\n\t\t\t\t\t}\n\t\t\t\t\td /= 10;\t\n\t\t\t\t}\n\t\t\tif(x / i != i) {\n\t\t\t\td = x / i;\n\t\t\t    bool ok = 1;\n\t\t\t\twhile(d) {\n\t\t\t\t\tfor(int i = 1; i <= l; i++)\n\t\t\t\t\t\tif(a[i] == d % 10) {\n\t\t\t\t\t\t\tok = 0;\n\t\t\t\t\t\t\tbreak;\n\t\t\t\t\t\t}\n\t\t\t\t\tif(!ok) {\n\t\t\t\t\t\tres++;\n\t\t\t\t\t\tbreak;\n\t\t\t\t\t}\n\t\t\t\t\td /= 10;\t\n\t\t\t\t}\n\t\t\t}\n\t\t\t\t\n\t\t}\n\t}\n\tcout << res;\n\treturn 0;\n}\n\t\t\n\n\t\t\t\t\t\t\n\t\n\n"], "input": "", "output": "", "tags": ["implementation"], "dificulty": "1300", "interactive": false}