{"link": "https://codeforces.com//contest/1162/problem/C", "problemId": "339906", "problem_idx": "C", "shortId": "1162C", "contest_number": "1162", "problem_submissions": {"F": [53760255], "E": [53755729, 53755411, 53755882, 53754129, 53757378, 53756764, 53757700, 53758454, 53758416, 53754833, 53757407, 53756313, 53758588, 53756165, 53758997, 53756619, 53758311, 53759677], "D": [53752747, 53753462, 53754325, 53757481, 53752843, 53755399, 53755520, 53755668, 53754940, 53755489, 53758915, 53755731, 53754946, 53755618, 53759491, 53755508, 53758786, 53755777, 53756167], "C": [53749836, 53750600, 53751425, 53750020, 53750391, 53752273, 53751033, 53751621, 53752004, 53752815, 53754220, 53751629, 53753641, 53751893, 53752886, 53751070, 53756767, 53753219], "B": [53748291, 53748052, 53748376, 53747817, 53748626, 53748146, 53748574, 53749401, 53805701, 53749421, 53749906, 53748692, 53758550, 53750610, 53749077, 53749412, 53749393, 53748736, 53751212], "A": [53746666, 53746560, 53746976, 53746641, 53746514, 53746879, 53746868, 53747863, 53805694, 53747143, 53747013, 53746924, 53746595, 53746573, 53747849, 53746548, 53747762, 53747182, 53748613]}, "name": "C. Hide and Seek", "statement": "Alice and Bob are playing a game on a line with n cells. There are n\r\ncells labeled from 1 through n. For each i from 1 to n-1, cells i and\r\ni+1 are adjacent.Alice initially has a token on some cell on the line,\r\nand Bob tries to guess where it is. Bob guesses a sequence of line cell\r\nnumbers x_1, x_2,\r\nldots, x_k in order. In the i-th question, Bob asks Alice if her token\r\nis currently on cell x_i. That is, Alice can answer either \"\" or \"\" to\r\neach Bob\u2019s question. in this process, before or after answering a\r\nquestion, Alice is allowed to move her token from her current cell to\r\nsome cell. Alice acted in such a way that she was able to answer \"\" to\r\nof Bob\u2019s questions.Note that Alice can even move her token before\r\nanswering the first question or after answering the last question. Alice\r\ncan also choose to not move at all.You are given n and Bob\u2019s questions\r\nx_1,\r\nldots, x_k. You would like to count the number of scenarios that let\r\nAlice answer \"\" to all of Bob\u2019s questions. Let (a,b) denote a scenario\r\nwhere Alice starts at cell a and ends at cell b. Two scenarios (a_i,\r\nb_i) and (a_j, b_j) are different if a_i\r\nneq a_j or b_i\r\nneq b_j.\r\n", "solutions": ["#include <cstdio>\n#include <vector>\n#include <algorithm>\n\nusing namespace std;\n\nint main()\n{\n    int N, K;\n    scanf(\"%d%d\", &N, &K);\n    vector<int> first(N, K + 1), last(N, -1);\n    for (int i = 0; i < K; ++i) {\n        int x;\n        scanf(\"%d\", &x);\n        x -= 1;\n        first[x] = min(first[x], i);\n        last[x] = max(last[x], i);\n    }\n\n    int ans = 0;\n    for (int i = 0; i < N; ++i) {\n        if (i > 0 && last[i - 1] <= first[i]) ans += 1;\n        if (i < N - 1 && last[i + 1] <= first[i]) ans += 1;\n        if (last[i] == -1) ans += 1;\n    }\n    printf(\"%d\\n\", ans);\n    return 0;\n}\n"], "input": "", "output": "", "tags": ["graphs", "implementation"], "dificulty": "1500", "interactive": false}