{
    "link": "https://codeforces.com//contest/239/problem/C",
    "problemId": "2118",
    "problem_idx": "C",
    "shortId": "239C",
    "contest_number": "239",
    "problem_submissions": {
        "E": [
            2503391,
            2503636,
            2508718,
            2504091,
            2504222,
            2503009,
            2503604,
            2504097,
            2504475,
            2508764,
            2503840
        ],
        "B": [
            2500622,
            2501438,
            2500637,
            2501733,
            2500564,
            2500710,
            2504655,
            2501496,
            2501817,
            2501834,
            2508769
        ],
        "C": [
            2500280,
            2499958,
            2501166,
            2500529,
            2502431,
            2501910,
            2500357,
            2500775,
            2504721,
            2502212,
            2502257,
            2500194,
            2502029,
            2500713,
            2500815,
            2500443,
            2501561,
            2504348
        ],
        "A": [
            2498489,
            2501638,
            2498087,
            2498849,
            2498385,
            2498220,
            2500674,
            2498079,
            2498264,
            2499139,
            2498265,
            2498039,
            2498269,
            2498638,
            2498174,
            2499123,
            2498500,
            2499003
        ],
        "D": [
            2504916,
            2503214,
            2503771,
            2503245,
            2503673,
            2503846,
            2504310,
            2504271
        ]
    },
    "name": "C. Not Wool Sequences",
    "statement": "A sequence of non-negative integers of length is called a if and only if\r\nthere exists two integers and such that . In other words each wool\r\nsequence contains a subsequence of consecutive elements with xor equal\r\nto 0.The expression means applying the operation of a bitwise xor to\r\nnumbers and . The given operation exists in all modern programming\r\nlanguages, for example, in languages and it is marked as \"\", in as \"\".In\r\nthis problem you are asked to compute the number of sequences made of\r\nintegers from 0 to that are not a wool sequence. You should print this\r\nnumber modulo .\r\n",
    "solutions": [
        "#include <stdio.h>\n#include <stdlib.h>\n#define mo 1000000009\n\nlong long n, m, Now, Ans, i;\n\nlong long sumi(long long a, long long b);\n\nint main()\n{\n\tscanf(\"%I64d %I64d\", &n, &m);\n\tNow = sumi(2, m);\n\tif (Now == 0)\n\t\tNow = mo - 1;\n\telse\n\t\tNow--;\n\tAns = 1;\n\tfor (i = 1; i <= n; i++)\n\t{\n\t\tAns *= Now;\n\t\tAns %= mo;\n\t\tif (Now == 0)\n\t\t\tNow = mo - 1;\n\t\telse\n\t\t\tNow--;\n\t}\n\t\n\tprintf(\"%I64d\\n\", Ans);\n\treturn 0;\n}\n\nlong long sumi(long long a, long long b)\n{\n\tlong long ret = 1, i, c = a;\n\tfor (i = 1; i <= b; i += i)\n\t{\n\t\tif ((b & i) > 0)\n\t\t{\n\t\t\tret *= c;\n\t\t\tret %= mo;\n\t\t}\n\t\t\n\t\tc *= c;\n\t\tc %= mo;\n\t}\n\t\n\treturn ret;\n}\n"
    ],
    "input": "",
    "output": "",
    "tags": [
        "combinatorics",
        "constructive algorithms",
        "math"
    ],
    "dificulty": "1300",
    "interactive": false,
    "file_name": "D:\\scoala\\RESEARCH\\MLCP\\01_CODEFORCES_DATASET\\DIV2\\C. Not Wool Sequences.json",
    "editorial_link": "https://codeforces.com//blog/entry/5765",
    "editorial": "Let a1,?...,?an be a not-wool-sequence. We define another sequence called b in which bi is xor of the first i elements of a,  and b0?=?0.\n\nNow xor of elements of a consecutive subsequence like ai,?...,?aj will be equal to . So we know that all elements of b should be different. Therefore b is a sequence of distinct integers of length n?+?1 starting with 0 made of numbers 0 to 2m?-?1. The number of such sequences is  and this is the answer to problem."
}