{"link": "https://codeforces.com//contest/699/problem/C", "problemId": "65784", "problem_idx": "C", "shortId": "699C", "contest_number": "699", "problem_submissions": {"F": [19254979], "D": [19246128, 19238145, 19243994, 19244671, 19244055, 19240256, 19244440, 19243946, 19242445, 19244114, 19244888, 19248232, 19245369, 19243420, 19242965, 19246841, 19244016, 19246279, 19245771, 19248614], "C": [19238575, 19234685, 19237143, 19235854, 19236952, 19235501, 19237560, 19233107, 19236256, 19238050, 19237219, 19240071, 19233148, 19236181, 19237922, 19238682, 19238483, 19238795, 19237556, 19239587], "B": [19235764, 19233222, 19235273, 19233766, 19234773, 19233727, 19234737, 19236748, 19232804, 19234744, 19234328, 19236200, 19240174, 19238029, 19236795, 19234746, 19234487, 19234011, 19235700, 19235759], "A": [19233122, 19232168, 19232143, 19232104, 19232384, 19232378, 19232697, 19238171, 19232180, 19232809, 19232842, 19233530, 19236710, 19232307, 19233403, 19232204, 19232321, 19232485, 19232270, 19233389]}, "name": "C. Vacations", "statement": "Vasya has days of vacations! So he decided to improve his IT skills and\r\ndo sport. Vasya knows the following information about each of this days:\r\nwhether that gym opened and whether a contest was carried out in the\r\nInternet on that day. For the -th day there are four options: on this\r\nday the gym is closed and the contest is not carried out; on this day\r\nthe gym is closed and the contest is carried out; on this day the gym is\r\nopen and the contest is not carried out; on this day the gym is open and\r\nthe contest is carried out. On each of days Vasya can either have a rest\r\nor write the contest (if it is carried out on this day), or do sport (if\r\nthe gym is open on this day).Find the minimum number of days on which\r\nVasya will have a rest (it means, he will not do sport and write the\r\ncontest at the same time). The only limitation that Vasya has .\r\n", "solutions": ["#include <stdio.h>\n#include <string.h>\n#include <stdlib.h>\n#include <time.h>\n#include <math.h>\n#include <iostream>\n#include <algorithm>\n#include <string>\n#include <set>\n#include <map>\n#include <queue>\n#include <stack>\n#include <vector>\n#include <bitset>\nusing namespace std;\n\n#define bll long long\n#define dou double\n#define For(i,a,b) for (int i=(a),_##i=(b); i<=_##i; i++)\n#define Rof(i,a,b) for (int i=(a),_##i=(b); i>=_##i; i--)\n#define rep(i,a,b) for (int i=(a),_##i=(b); i<=_##i; i++)\n#define rek(i,a,b) for (int i=(a),_##i=(b); i>=_##i; i--)\n#define Mem(a,b) memset(a,b,sizeof(a))\n#define Cpy(a,b) memcpy(a,b,sizeof(b))\n//__builtin_popcountll\n\nconst int maxn=100+10,oo=1<<30;\nint N,A[maxn],F[maxn][3];\n\nint main(int argc, char* argv[])\n{\n    for (; scanf(\"%d\",&N)!=EOF; )\n    {\n        For(i,1,N) scanf(\"%d\",&A[i]);\n        For(i,1,N) For(j,0,2) F[i][j]=oo;\n        F[0][2]=0;\n        For(i,1,N)\n        {\n            For(j,0,2)\n                if (F[i-1][j]!=oo)\n                {\n                    if ((A[i]&1) && j!=0) F[i][0]=min(F[i][0],F[i-1][j]);\n                    if ((A[i]&2) && j!=1) F[i][1]=min(F[i][1],F[i-1][j]);\n                    F[i][2]=min(F[i][2],F[i-1][j]+1);\n                }\n        }\n        int ans=min(F[N][0],min(F[N][1],F[N][2]));\n        printf(\"%d\\n\",ans);\n    }\n    return 0;\n}"], "input": "", "output": "", "tags": ["brute force", "dp"], "dificulty": "1400", "interactive": false}