{"link": "https://codeforces.com//contest/509/problem/E", "problemId": "21541", "problem_idx": "E", "shortId": "509E", "contest_number": "509", "problem_submissions": {"F": [9650295, 9648525, 9652941, 66412652, 9656510, 9654779, 9656634], "D": [9649357, 9654774, 17987388, 9655232, 9650962, 9652519, 9653543, 9654747, 9652061, 9654982, 9653984, 9647661, 9657026, 9650855], "E": [9647331, 9646822, 9648254, 9648062, 9650747, 9650969, 9652383, 9648899, 9651327, 9650674, 9650867, 9649973, 9651180, 9649729, 9651615, 9648041, 9654967, 9654814, 9654669, 9653966, 9647539], "C": [9645828, 9652330, 9645693, 9644588, 9646725, 9649235, 9647186, 9656672, 9648094, 9645838, 9646105, 9648771, 9647552, 9649596, 9652387, 9650184, 9650446], "B": [9642318, 9650812, 9644457, 9646310, 9647229, 9643332, 9648725, 9645322, 9642950, 9643872, 9643385, 9643757, 9643187, 9643245, 9644721, 9645020, 9642364, 9643723, 9651476], "A": [9640468, 9644536, 9640418, 9640550, 9640578, 9642285, 9643656, 9644283, 9640433, 9640454, 9641139, 9641249, 9640654, 9640465, 9642716, 9641084, 9640702, 9640994, 9640877]}, "name": "E. Pretty Song", "statement": "When Sasha was studying in the seventh grade, he started listening to\r\nmusic a lot. In order to evaluate which songs he likes more, he\r\nintroduced the notion of the song\u2019s . The title of the song is a word\r\nconsisting of uppercase Latin letters. The of the song is the of its\r\ntitle.Let\u2019s define the of a word as the ratio of the number of vowels in\r\nthe word to the number of all letters in the word.Let\u2019s define the of a\r\nword as the sum of of all the substrings of the word.More formally,\r\nlet\u2019s define the function which is equal to , if is a vowel, and to\r\notherwise. Let be the -th character of string , and be the substring of\r\nword , staring at the -th character and ending at the -th character (,\r\n).Then the of is defined by the formula:The of equals Find the of the\r\ngiven song title.We assume that the vowels are .\r\n", "solutions": ["#include<iostream>\n#include<algorithm>\n#include<cstdio>\n#include<cmath>\n#include<cstring>\n#include<queue>\n#include<vector>\n#include<cstdlib>\n#include<set>\nusing namespace std;\n#define N 510000\nchar str[N];\nlong long s1[N],s2[N],s3[N];\ndouble ans=0;\nint n;\nbool pd(char ch){\n     return ch=='I' || ch=='E' || ch=='A' || ch=='O' || ch=='U' || ch=='Y';\n     }\nint main(){\n    scanf(\"%s\",str);\n    n=strlen(str);\n    for(int i=1;i<=n;i++)\n      if(pd(str[i-1])){\n        int t1=min(i,n-i+1),t2=max(i,n-i+1);\n        s1[1]++;\n        s1[t1]--;\n        s2[t1]+=t1;\n        s2[t2+1]-=t1;\n        s3[n]++;\n        s3[t2]--;          \n      }\n    for(int i=1;i<=n;i++)s1[i]+=s1[i-1],s2[i]+=s2[i-1];\n    for(int i=n;i;i--)s3[i]+=s3[i+1];\n    for(int i=1;i<=n;i++){\n      long long s=s1[i]*i+s2[i]+s3[i]*(n-i+1);\n      ans+=(double)s/i;\n    }\n    printf(\"%.7lf\\n\",ans);\n    return 0;\n}\n"], "input": "", "output": "", "tags": ["math", "strings"], "dificulty": "2000", "interactive": false}